{
    "post_title": "Hum Dil De Chuke Sanam (1999)",
    "post_type": "movie",
    "tmdb_id": 5319,
    "imdb_id": "tt0150992",
    "languages": [
        "Hindi"
    ],
    "links": {
        "480p": [
            {
                "episode_title": "Episode 1",
                "link": "https://vcloud.zip/5dqd11nnz67121j"
            }
        ],
        "720p": [
            {
                "episode_title": "Episode 1",
                "link": "https://vcloud.zip/f8s8kcpq_qzin_m"
            }
        ],
        "1080p": [
            {
                "episode_title": "Episode 1",
                "link": "https://vcloud.zip/u3dd6zcgmzismi1"
            }
        ]
    }
}