{
    "post_title": "Jaanam Samjha Karo (1999)",
    "post_type": "movie",
    "tmdb_id": 161227,
    "imdb_id": "tt0226847",
    "languages": [
        "Hindi"
    ],
    "links": {
        "480p": [
            {
                "episode_title": "Episode 1",
                "link": "https://vcloud.zip/06oiauw1zu6pxux"
            }
        ],
        "720p": [
            {
                "episode_title": "Episode 1",
                "link": "https://vcloud.zip/tgq--bawpctbwnt"
            }
        ],
        "1080p": [
            {
                "episode_title": "Episode 1",
                "link": "https://vcloud.zip/11wegebw5twsxx5"
            }
        ]
    }
}