{
    "post_title": "Mashaal (1984)",
    "post_type": "movie",
    "tmdb_id": 206202,
    "imdb_id": "tt0085912",
    "languages": [
        "Hindi"
    ],
    "links": {
        "480p": [
            {
                "episode_title": "Episode 1",
                "link": "https://vcloud.zip/9-h7hu494979peo"
            }
        ],
        "720p": [
            {
                "episode_title": "Episode 1",
                "link": "https://vcloud.zip/54snfkczxsckoxo"
            }
        ],
        "1080p": [
            {
                "episode_title": "Episode 1",
                "link": "https://vcloud.zip/cububuntnoenuv3"
            }
        ]
    }
}