{
    "post_title": "Naari Naari Naduma Murari (2026)",
    "post_type": "movie",
    "tmdb_id": 1417849,
    "imdb_id": "tt29638896",
    "languages": [
        "Hindi",
        "Telugu"
    ],
    "links": {
        "480p": [
            {
                "episode_title": "Episode 1",
                "link": "https://vcloud.zip/uhmgc1g1vzm1uvj"
            }
        ],
        "720p": [
            {
                "episode_title": "Episode 1",
                "link": "https://vcloud.zip/kmryklkikk1q2kk"
            }
        ],
        "1080p": [
            {
                "episode_title": "Episode 1",
                "link": "https://vcloud.zip/ajeujwlwuad30k1"
            }
        ]
    }
}