{
    "post_title": "Oh Darling! Yeh Hai India! (1995)",
    "post_type": "movie",
    "tmdb_id": 160243,
    "imdb_id": "tt0114031",
    "languages": [
        "Hindi"
    ],
    "links": {
        "480p": [
            {
                "episode_title": "Episode 1",
                "link": "https://vcloud.zip/ayofmuv0pymbllq"
            }
        ],
        "720p": [
            {
                "episode_title": "Episode 1",
                "link": "https://vcloud.zip/qzdzcqsz_bbemca"
            },
            {
                "episode_title": "Episode 2",
                "link": "https://vcloud.zip/v3zv_zhjz38rmin"
            }
        ],
        "1080p": [
            {
                "episode_title": "Episode 1",
                "link": "https://vcloud.zip/suunfueae6mgtzl"
            }
        ]
    }
}