{
    "post_title": "Shwetkali (2023)",
    "post_type": "series",
    "tmdb_id": 221107,
    "imdb_id": "tt26744306",
    "languages": [
        "Bengali"
    ],
    "total_seasons": 1,
    "seasons": {
        "1": {
            "480p": [
                {
                    "episode_title": "Episode 1",
                    "link": "https://vcloud.zip/s9urdcs7_q3dg57"
                }
            ],
            "720p": [
                {
                    "episode_title": "Episode 1",
                    "link": "https://vcloud.zip/qdftktbbk66p_vf"
                }
            ]
        }
    }
}