{
    "post_title": "Siddharth (2013)",
    "post_type": "movie",
    "tmdb_id": 212754,
    "imdb_id": "tt2932606",
    "languages": [
        "Hindi"
    ],
    "links": {
        "480p": [
            {
                "episode_title": "Episode 1",
                "link": "https://vcloud.zip/pirve6e3jvicc93"
            }
        ],
        "720p": [
            {
                "episode_title": "Episode 1",
                "link": "https://vcloud.zip/g1wkmwttcttzwzv"
            }
        ],
        "1080p": [
            {
                "episode_title": "Episode 1",
                "link": "https://vcloud.zip/iqffg33hs9jhff9"
            }
        ]
    }
}