{
    "post_title": "The Chargesheet: Innocent or Guilty? (2020)",
    "post_type": "series",
    "tmdb_id": 97120,
    "imdb_id": "tt11535184",
    "languages": [
        "Hindi"
    ],
    "total_seasons": 1,
    "seasons": {
        "1": {
            "480p": [
                {
                    "episode_title": "Episode 1",
                    "link": "https://vcloud.zip/14x21_elliiruwo"
                },
                {
                    "episode_title": "Episode 2",
                    "link": "https://vcloud.zip/gmbizdyy5wamigy"
                }
            ],
            "720p": [
                {
                    "episode_title": "Episode 1",
                    "link": "https://vcloud.zip/pykcnyx-xhp25vx"
                },
                {
                    "episode_title": "Episode 2",
                    "link": "https://vcloud.zip/8tr3lrred7mr5u2"
                }
            ]
        }
    }
}