{
    "post_title": "Tirangaa (1993)",
    "post_type": "movie",
    "tmdb_id": 272662,
    "imdb_id": "tt0105599",
    "languages": [
        "Hindi"
    ],
    "links": {
        "480p": [
            {
                "episode_title": "Episode 1",
                "link": "https://vcloud.zip/oex5dlaqprorobp"
            }
        ],
        "720p": [
            {
                "episode_title": "Episode 1",
                "link": "https://vcloud.zip/iiyl1ycnsvlwsvb"
            }
        ],
        "1080p": [
            {
                "episode_title": "Episode 1",
                "link": "https://vcloud.zip/pp81778qb218yhf"
            }
        ]
    }
}