{
  "id": "TO01568195",
  "type": "movie",
  "title": "Doosri Maa",
  "poster": "https://encrypted-tbn0.gstatic.com/images?q=tbn:ANd9GcR0wXjttTDVwHRQ7Ps0TGFX7tC6BRYw2mljsg&s",
  "backdrop": "https://i.ytimg.com/vi/hLCd36Js210/maxresdefault.jpg",
  "year": "2025",
  "result": "HD",
  "language": [
    "HINDI"
  ],
  "watch": "<iframe src=\"https://bysebuho.com/e/3ymp9d6zs23g/doosri-maa-2025-720p-uplay-web-dl-aac2-0-h-264\" frameborder=\"0\" marginwidth=\"0\" marginheight=\"0\" scrolling=\"no\" width=\"640\" height=\"360\" allowfullscreen></iframe>"
}