{
    "post_title": "Music by John Williams (2024)",
    "post_type": "movie",
    "tmdb_id": 1076708,
    "imdb_id": "tt26420234",
    "languages": [
        "English",
        "With",
        "Subtitles"
    ],
    "links": {
        "720p": [
            {
                "episode_title": "Episode 1",
                "link": "https://vcloud.zip/5u06h6o6qnc7h6u"
            }
        ],
        "1080p": [
            {
                "episode_title": "Episode 1",
                "link": "https://vcloud.zip/4b0hh2prw1kahmb"
            }
        ]
    }
}