{
  "id": "245827",
  "type": "tv",
  "title": "Harlan Coben's Lazarus",
  "poster": "https://image.tmdb.org/t/p/w342/lxUlUBGnYJNxqOwc3baBdLpa3Lx.jpg",
  "backdrop": "https://image.tmdb.org/t/p/original/uj4wyiZPmZNRJBjThtqNrZvHN9w.jpg",
  "year": "2025",
  "result": "HD",
  "language": [
    "Hindi"
  ],
  "seasons": [
    {
      "season_number": 1,
      "episodes": [
        {
          "episode_number": 1,
          "watch": "<iframe src=\"https://bysebuho.com/e/g5r7z3wm19bz/harlan-cobens-lazarus-2025-hin-eng-s01-e01-720p-daniewatch\" frameborder=\"0\" marginwidth=\"0\" marginheight=\"0\" scrolling=\"no\" width=\"640\" height=\"360\" allowfullscreen></iframe>"
        },
        {
          "episode_number": 2,
          "watch": "<iframe src=\"https://bysebuho.com/e/uayekjivdupn/harlan-cobens-lazarus-2025-hin-eng-s01-e02-720p-daniewatch\" frameborder=\"0\" marginwidth=\"0\" marginheight=\"0\" scrolling=\"no\" width=\"640\" height=\"360\" allowfullscreen></iframe>"
        },
        {
          "episode_number": 3,
          "watch": "<iframe src=\"https://bysebuho.com/e/ad5crkp3z1rm/harlan-cobens-lazarus-2025-hin-eng-s01-e03-720p-daniewatch\" frameborder=\"0\" marginwidth=\"0\" marginheight=\"0\" scrolling=\"no\" width=\"640\" height=\"360\" allowfullscreen></iframe>"
        },
        {
          "episode_number": 4,
          "watch": "<iframe src=\"https://bysebuho.com/e/jaze0w3gmyk3/harlan-cobens-lazarus-2025-hin-eng-s01-e04-720p-daniewatch\" frameborder=\"0\" marginwidth=\"0\" marginheight=\"0\" scrolling=\"no\" width=\"640\" height=\"360\" allowfullscreen></iframe>"
        },
        {
          "episode_number": 5,
          "watch": "<iframe src=\"https://bysebuho.com/e/lti2nf3sz0ul/harlan-cobens-lazarus-2025-hin-eng-s01-e05-720p-daniewatch\" frameborder=\"0\" marginwidth=\"0\" marginheight=\"0\" scrolling=\"no\" width=\"640\" height=\"360\" allowfullscreen></iframe>"
        },
        {
          "episode_number": 6,
          "watch": "<iframe src=\"https://bysebuho.com/e/w1p737xikqq1/harlan-cobens-lazarus-2025-hin-eng-s01-e06-720p-daniewatch\" frameborder=\"0\" marginwidth=\"0\" marginheight=\"0\" scrolling=\"no\" width=\"640\" height=\"360\" allowfullscreen></iframe>"
        }
      ]
    }
  ]
}