{
  "id": "105214",
  "type": "tv",
  "title": "Dark Desire",
  "poster": "https://image.tmdb.org/t/p/w342/uxFNAo2A6ZRcgNASLk02hJUbybn.jpg",
  "backdrop": "https://image.tmdb.org/t/p/original/9CBdzw7CK2m6WpfEfqe73V8i5O0.jpg",
  "year": "2020",
  "result": "HD",
  "language": [
    "Hindi"
  ],
  "seasons": [
    {
      "season_number": 1,
      "episodes": [
        {
          "episode_number": 1,
          "watch": "<iframe src=\"https://bysebuho.com/e/fk05pyqdjk78/dark-desire-s01-e01-720p-10bit-web-dl-hindi-5-1-spanish-hevc-x265-daniewatch-nl\" frameborder=\"0\" marginwidth=\"0\" marginheight=\"0\" scrolling=\"no\" width=\"640\" height=\"360\" allowfullscreen></iframe>"
        },
        {
          "episode_number": 2,
          "watch": "<iframe src=\"https://bysebuho.com/e/nefgigd54gts/dark-desire-s01-e02-720p-10bit-web-dl-hindi-5-1-spanish-hevc-x265-daniewatch-nl\" frameborder=\"0\" marginwidth=\"0\" marginheight=\"0\" scrolling=\"no\" width=\"640\" height=\"360\" allowfullscreen></iframe>"
        },
        {
          "episode_number": 3,
          "watch": "<iframe src=\"https://bysebuho.com/e/t6s0lx6j1ugo/dark-desire-s01-e03-720p-10bit-web-dl-hindi-5-1-spanish-hevc-x265-daniewatch-nl\" frameborder=\"0\" marginwidth=\"0\" marginheight=\"0\" scrolling=\"no\" width=\"640\" height=\"360\" allowfullscreen></iframe>"
        },
        {
          "episode_number": 4,
          "watch": "<iframe src=\"https://bysebuho.com/e/lplomdrzncl9/dark-desire-s01-e04-720p-10bit-web-dl-hindi-5-1-spanish-hevc-x265-daniewatch-nl\" frameborder=\"0\" marginwidth=\"0\" marginheight=\"0\" scrolling=\"no\" width=\"640\" height=\"360\" allowfullscreen></iframe>"
        },
        {
          "episode_number": 5,
          "watch": "<iframe src=\"https://bysebuho.com/e/c09jvhtp0fud/dark-desire-s01-e05-720p-10bit-web-dl-hindi-5-1-spanish-hevc-x265-daniewatch-nl\" frameborder=\"0\" marginwidth=\"0\" marginheight=\"0\" scrolling=\"no\" width=\"640\" height=\"360\" allowfullscreen></iframe>"
        },
        {
          "episode_number": 6,
          "watch": "<iframe src=\"https://bysebuho.com/e/dcwuhl38j2sw/dark-desire-s01-e06-720p-10bit-web-dl-hindi-5-1-spanish-hevc-x265-daniewatch-nl\" frameborder=\"0\" marginwidth=\"0\" marginheight=\"0\" scrolling=\"no\" width=\"640\" height=\"360\" allowfullscreen></iframe>"
        },
        {
          "episode_number": 7,
          "watch": "<iframe src=\"https://bysebuho.com/e/ypg9178annm1/dark-desire-s01-e07-720p-10bit-web-dl-hindi-5-1-spanish-hevc-x265-daniewatch-nl\" frameborder=\"0\" marginwidth=\"0\" marginheight=\"0\" scrolling=\"no\" width=\"640\" height=\"360\" allowfullscreen></iframe>"
        },
        {
          "episode_number": 8,
          "watch": "<iframe src=\"https://bysebuho.com/e/914lnnygvoru/dark-desire-s01-e08-720p-10bit-web-dl-hindi-5-1-spanish-hevc-x265-daniewatch-nl\" frameborder=\"0\" marginwidth=\"0\" marginheight=\"0\" scrolling=\"no\" width=\"640\" height=\"360\" allowfullscreen></iframe>"
        },
        {
          "episode_number": 9,
          "watch": "<iframe src=\"https://bysebuho.com/e/of42974apmv4/dark-desire-s01-e09-720p-10bit-web-dl-hindi-5-1-spanish-hevc-x265-daniewatch-nl\" frameborder=\"0\" marginwidth=\"0\" marginheight=\"0\" scrolling=\"no\" width=\"640\" height=\"360\" allowfullscreen></iframe>"
        },
        {
          "episode_number": 10,
          "watch": "<iframe src=\"https://bysebuho.com/e/zi0bjcv515rp/dark-desire-s01-e10-720p-10bit-web-dl-hindi-5-1-spanish-hevc-x265-daniewatch-nl\" frameborder=\"0\" marginwidth=\"0\" marginheight=\"0\" scrolling=\"no\" width=\"640\" height=\"360\" allowfullscreen></iframe>"
        },
        {
          "episode_number": 11,
          "watch": "<iframe src=\"https://bysebuho.com/e/a3u8g9nijldz/dark-desire-s01-e11-720p-10bit-web-dl-hindi-5-1-spanish-hevc-x265-daniewatch-nl\" frameborder=\"0\" marginwidth=\"0\" marginheight=\"0\" scrolling=\"no\" width=\"640\" height=\"360\" allowfullscreen></iframe>"
        },
        {
          "episode_number": 12,
          "watch": "<iframe src=\"https://bysebuho.com/e/aya0jqre5rzk/dark-desire-s01-e12-720p-10bit-web-dl-hindi-5-1-spanish-hevc-x265-daniewatch-nl\" frameborder=\"0\" marginwidth=\"0\" marginheight=\"0\" scrolling=\"no\" width=\"640\" height=\"360\" allowfullscreen></iframe>"
        },
        {
          "episode_number": 13,
          "watch": "<iframe src=\"https://bysebuho.com/e/o814rljbh5fh/dark-desire-s01-e13-720p-10bit-web-dl-hindi-5-1-spanish-hevc-x265-daniewatch-nl\" frameborder=\"0\" marginwidth=\"0\" marginheight=\"0\" scrolling=\"no\" width=\"640\" height=\"360\" allowfullscreen></iframe>"
        },
        {
          "episode_number": 14,
          "watch": "<iframe src=\"https://bysebuho.com/e/cjfo26evym3c/dark-desire-s01-e14-720p-10bit-web-dl-hindi-5-1-spanish-hevc-x265-daniewatch-nl\" frameborder=\"0\" marginwidth=\"0\" marginheight=\"0\" scrolling=\"no\" width=\"640\" height=\"360\" allowfullscreen></iframe>"
        },
        {
          "episode_number": 15,
          "watch": "<iframe src=\"https://bysebuho.com/e/hzv20tbdiod7/dark-desire-s01-e15-720p-10bit-web-dl-hindi-5-1-spanish-hevc-x265-daniewatch-nl\" frameborder=\"0\" marginwidth=\"0\" marginheight=\"0\" scrolling=\"no\" width=\"640\" height=\"360\" allowfullscreen></iframe>"
        },
        {
          "episode_number": 16,
          "watch": "<iframe src=\"https://bysebuho.com/e/itdc9c389sgn/dark-desire-s01-e16-720p-10bit-web-dl-hindi-5-1-spanish-hevc-x265-daniewatch-nl\" frameborder=\"0\" marginwidth=\"0\" marginheight=\"0\" scrolling=\"no\" width=\"640\" height=\"360\" allowfullscreen></iframe>"
        },
        {
          "episode_number": 17,
          "watch": "<iframe src=\"https://bysebuho.com/e/ytvarrrr4ukj/dark-desire-s01-e17-720p-10bit-web-dl-hindi-5-1-spanish-hevc-x265-daniewatch-nl\" frameborder=\"0\" marginwidth=\"0\" marginheight=\"0\" scrolling=\"no\" width=\"640\" height=\"360\" allowfullscreen></iframe>"
        },
        {
          "episode_number": 18,
          "watch": "<iframe src=\"https://bysebuho.com/e/rjzufrkj816d/dark-desire-s01-e18-720p-10bit-web-dl-hindi-5-1-spanish-hevc-x265-daniewatch-nl\" frameborder=\"0\" marginwidth=\"0\" marginheight=\"0\" scrolling=\"no\" width=\"640\" height=\"360\" allowfullscreen></iframe>"
        }
      ]
    },
    {
      "season_number": 2,
      "episodes": [
        {
          "episode_number": 1,
          "watch": "<iframe src=\"https://bysebuho.com/e/rcpfhfg2axso/dark-desire-s02e01-eros-and-psyche-720p-nf-web-dl-aac2-0-x264-daniewatch-nl\" frameborder=\"0\" marginwidth=\"0\" marginheight=\"0\" scrolling=\"no\" width=\"640\" height=\"360\" allowfullscreen></iframe>"
        },
        {
          "episode_number": 2,
          "watch": "<iframe src=\"https://bysebuho.com/e/dsa6203949qv/dark-desire-s02e02-you-can-never-escape-something-like-this-720p-nf-web-dl-aac2-0-x264-daniewatch-nl\" frameborder=\"0\" marginwidth=\"0\" marginheight=\"0\" scrolling=\"no\" width=\"640\" height=\"360\" allowfullscreen></iframe>"
        },
        {
          "episode_number": 3,
          "watch": "<iframe src=\"https://bysebuho.com/e/auwlx8k6jka9/dark-desire-s02e03-no-one-can-run-from-themselves-720p-nf-web-dl-aac2-0-x264-daniewatch-nl\" frameborder=\"0\" marginwidth=\"0\" marginheight=\"0\" scrolling=\"no\" width=\"640\" height=\"360\" allowfullscreen></iframe>"
        },
        {
          "episode_number": 4,
          "watch": "<iframe src=\"https://bysebuho.com/e/jb37bu4z3ike/dark-desire-s02e04-the-other-720p-nf-web-dl-aac2-0-x264-daniewatch-nl\" frameborder=\"0\" marginwidth=\"0\" marginheight=\"0\" scrolling=\"no\" width=\"640\" height=\"360\" allowfullscreen></iframe>"
        },
        {
          "episode_number": 5,
          "watch": "<iframe src=\"https://bysebuho.com/e/wscx2sfvfxkd/dark-desire-s02e05-walking-on-hot-coals-720p-nf-web-dl-aac2-0-x264-daniewatch-nl\" frameborder=\"0\" marginwidth=\"0\" marginheight=\"0\" scrolling=\"no\" width=\"640\" height=\"360\" allowfullscreen></iframe>"
        },
        {
          "episode_number": 6,
          "watch": "<iframe src=\"https://bysebuho.com/e/885qsrhnizln/dark-desire-s02e06-you-were-always-my-mirror-720p-nf-web-dl-aac2-0-x264-daniewatch-nl\" frameborder=\"0\" marginwidth=\"0\" marginheight=\"0\" scrolling=\"no\" width=\"640\" height=\"360\" allowfullscreen></iframe>"
        },
        {
          "episode_number": 7,
          "watch": "<iframe src=\"https://bysebuho.com/e/6ze6pbbeu645/dark-desire-s02e07-a-dangerous-cocktail-720p-nf-web-dl-aac2-0-x264-daniewatch-nl\" frameborder=\"0\" marginwidth=\"0\" marginheight=\"0\" scrolling=\"no\" width=\"640\" height=\"360\" allowfullscreen></iframe>"
        },
        {
          "episode_number": 8,
          "watch": "<iframe src=\"https://bysebuho.com/e/9pbbeyl63hzj/dark-desire-s02e08-dont-believe-a-thing-you-hear-720p-nf-web-dl-aac2-0-x264-daniewatch-nl\" frameborder=\"0\" marginwidth=\"0\" marginheight=\"0\" scrolling=\"no\" width=\"640\" height=\"360\" allowfullscreen></iframe>"
        },
        {
          "episode_number": 9,
          "watch": "<iframe src=\"https://bysebuho.com/e/6bogtz7zrrqd/dark-desire-s02e09-youve-become-your-own-worst-enemy-720p-nf-web-dl-aac2-0-x264-daniewatch-nl\" frameborder=\"0\" marginwidth=\"0\" marginheight=\"0\" scrolling=\"no\" width=\"640\" height=\"360\" allowfullscreen></iframe>"
        },
        {
          "episode_number": 10,
          "watch": "<iframe src=\"https://bysebuho.com/e/ohmbnb7gbyqr/dark-desire-s02e10-everyone-reads-their-own-story-720p-nf-web-dl-aac2-0-x264-daniewatch-nl\" frameborder=\"0\" marginwidth=\"0\" marginheight=\"0\" scrolling=\"no\" width=\"640\" height=\"360\" allowfullscreen></iframe>"
        },
        {
          "episode_number": 11,
          "watch": "<iframe src=\"https://bysebuho.com/e/jn31zhakqu7v/dark-desire-s02e11-who-the-x-and-are-you-really-720p-nf-web-dl-aac2-0-x264-daniewatch-nl\" frameborder=\"0\" marginwidth=\"0\" marginheight=\"0\" scrolling=\"no\" width=\"640\" height=\"360\" allowfullscreen></iframe>"
        },
        {
          "episode_number": 12,
          "watch": "<iframe src=\"https://bysebuho.com/e/212bxjqx9eab/dark-desire-s02e12-the-twins-720p-nf-web-dl-aac2-0-x264-daniewatch-nl\" frameborder=\"0\" marginwidth=\"0\" marginheight=\"0\" scrolling=\"no\" width=\"640\" height=\"360\" allowfullscreen></iframe>"
        },
        {
          "episode_number": 13,
          "watch": "<iframe src=\"https://bysebuho.com/e/n27m8r0m78r3/dark-desire-s02e13-a-perfect-and-unbearable-triangle-720p-nf-web-dl-aac2-0-x264-daniewatch-nl\" frameborder=\"0\" marginwidth=\"0\" marginheight=\"0\" scrolling=\"no\" width=\"640\" height=\"360\" allowfullscreen></iframe>"
        },
        {
          "episode_number": 14,
          "watch": "<iframe src=\"https://bysebuho.com/e/qyndxlnlrrlf/dark-desire-s02e14-it-was-always-you-720p-nf-web-dl-aac2-0-x264-daniewatch-nl\" frameborder=\"0\" marginwidth=\"0\" marginheight=\"0\" scrolling=\"no\" width=\"640\" height=\"360\" allowfullscreen></iframe>"
        },
        {
          "episode_number": 15,
          "watch": "<iframe src=\"https://bysebuho.com/e/g520h6bkdi8v/dark-desire-s02e15-facing-the-darkness-720p-nf-web-dl-aac2-0-x264-daniewatch-nl\" frameborder=\"0\" marginwidth=\"0\" marginheight=\"0\" scrolling=\"no\" width=\"640\" height=\"360\" allowfullscreen></iframe>"
        }
      ]
    }
  ],
  "release_date": "2020-07-15"
}