{
  "id": "1444973",
  "type": "movie",
  "title": "Jatadhara",
  "poster": "https://image.tmdb.org/t/p/w342/91aJa79gHiTUWh86XFRMaD2MGjj.jpg",
  "backdrop": "https://image.tmdb.org/t/p/original/l9Xe6L1QuM5DQsSthMPN3yPwfJK.jpg",
  "year": "2025",
  "result": "HD",
  "language": [
    "Hindi"
  ],
  "watch": "<iframe src=\"https://bysebuho.com/e/6tgov59i9ows/Jatadhara__2025__Hindi_HDTC_720p_-_DANIEWATCH\" frameborder=\"0\" marginwidth=\"0\" marginheight=\"0\" scrolling=\"no\" width=\"640\" height=\"360\" allowfullscreen></iframe>"
}