{
  "id": "230923",
  "type": "tv",
  "title": "Lovely Runner",
  "poster": "https://image.tmdb.org/t/p/w342/xJQyrif5M4UMoVBrBlwUabtaRxB.jpg",
  "backdrop": "https://image.tmdb.org/t/p/original/vbkpl0ps4s5tMTUnC7SFXNzWmVr.jpg",
  "year": "2024",
  "result": "HD",
  "language": [
    "Hindi"
  ],
  "seasons": [
    {
      "season_number": 1,
      "episodes": [
        {
          "episode_number": 1,
          "watch": "<iframe src=\"https://bysebuho.com/e/949awmlvd54j/lovely-runner-s01e01-720p-amzn-web-dl-ddp2-0-h-264-daniewatch\" frameborder=\"0\" marginwidth=\"0\" marginheight=\"0\" scrolling=\"no\" width=\"640\" height=\"360\" allowfullscreen></iframe>"
        },
        {
          "episode_number": 2,
          "watch": "<iframe src=\"https://bysebuho.com/e/hpfxsc9vjaui/lovely-runner-s01e02-720p-amzn-web-dl-ddp2-0-h-264-daniewatch\" frameborder=\"0\" marginwidth=\"0\" marginheight=\"0\" scrolling=\"no\" width=\"640\" height=\"360\" allowfullscreen></iframe>"
        },
        {
          "episode_number": 3,
          "watch": "<iframe src=\"https://bysebuho.com/e/13h55eduj0kj/lovely-runner-s01e03-720p-amzn-web-dl-ddp2-0-h-264-daniewatch\" frameborder=\"0\" marginwidth=\"0\" marginheight=\"0\" scrolling=\"no\" width=\"640\" height=\"360\" allowfullscreen></iframe>"
        },
        {
          "episode_number": 4,
          "watch": "<iframe src=\"https://bysebuho.com/e/yncrowoyzxmw/lovely-runner-s01e04-720p-amzn-web-dl-ddp2-0-h-264-daniewatch\" frameborder=\"0\" marginwidth=\"0\" marginheight=\"0\" scrolling=\"no\" width=\"640\" height=\"360\" allowfullscreen></iframe>"
        },
        {
          "episode_number": 5,
          "watch": "<iframe src=\"https://bysebuho.com/e/3tfb0pxq6rec/lovely-runner-s01e05-720p-amzn-web-dl-ddp2-0-h-264-daniewatch\" frameborder=\"0\" marginwidth=\"0\" marginheight=\"0\" scrolling=\"no\" width=\"640\" height=\"360\" allowfullscreen></iframe>"
        },
        {
          "episode_number": 6,
          "watch": "<iframe src=\"https://bysebuho.com/e/r2dn6lgun445/lovely-runner-s01e06-720p-amzn-web-dl-ddp2-0-h-264-daniewatch\" frameborder=\"0\" marginwidth=\"0\" marginheight=\"0\" scrolling=\"no\" width=\"640\" height=\"360\" allowfullscreen></iframe>"
        },
        {
          "episode_number": 7,
          "watch": "<iframe src=\"https://bysebuho.com/e/cf5pkhargp07/lovely-runner-s01e07-720p-amzn-web-dl-ddp2-0-h-264-daniewatch\" frameborder=\"0\" marginwidth=\"0\" marginheight=\"0\" scrolling=\"no\" width=\"640\" height=\"360\" allowfullscreen></iframe>"
        },
        {
          "episode_number": 8,
          "watch": "<iframe src=\"https://bysebuho.com/e/h6gb96scbylg/lovely-runner-s01e08-720p-amzn-web-dl-ddp2-0-h-264-daniewatch\" frameborder=\"0\" marginwidth=\"0\" marginheight=\"0\" scrolling=\"no\" width=\"640\" height=\"360\" allowfullscreen></iframe>"
        },
        {
          "episode_number": 9,
          "watch": "<iframe src=\"https://bysebuho.com/e/y55mfy4632to/lovely-runner-s01e09-720p-amzn-web-dl-ddp2-0-h-264-daniewatch\" frameborder=\"0\" marginwidth=\"0\" marginheight=\"0\" scrolling=\"no\" width=\"640\" height=\"360\" allowfullscreen></iframe>"
        },
        {
          "episode_number": 10,
          "watch": "<iframe src=\"https://bysebuho.com/e/zs8vv5raxifc/lovely-runner-s01e10-720p-amzn-web-dl-ddp2-0-h-264-daniewatch\" frameborder=\"0\" marginwidth=\"0\" marginheight=\"0\" scrolling=\"no\" width=\"640\" height=\"360\" allowfullscreen></iframe>"
        },
        {
          "episode_number": 11,
          "watch": "<iframe src=\"https://bysebuho.com/e/aiw273t1a57i/lovely-runner-s01e11-720p-amzn-web-dl-ddp2-0-h-264-daniewatch\" frameborder=\"0\" marginwidth=\"0\" marginheight=\"0\" scrolling=\"no\" width=\"640\" height=\"360\" allowfullscreen></iframe>"
        },
        {
          "episode_number": 12,
          "watch": "<iframe src=\"https://bysebuho.com/e/2mbwg3u5e1yj/lovely-runner-s01e12-720p-amzn-web-dl-ddp2-0-h-264-daniewatch\" frameborder=\"0\" marginwidth=\"0\" marginheight=\"0\" scrolling=\"no\" width=\"640\" height=\"360\" allowfullscreen></iframe>"
        },
        {
          "episode_number": 13,
          "watch": "<iframe src=\"https://bysebuho.com/e/i5rqydmzqmqm/lovely-runner-s01e13-720p-amzn-web-dl-ddp2-0-h-264-daniewatch\" frameborder=\"0\" marginwidth=\"0\" marginheight=\"0\" scrolling=\"no\" width=\"640\" height=\"360\" allowfullscreen></iframe>"
        },
        {
          "episode_number": 14,
          "watch": "<iframe src=\"https://bysebuho.com/e/0heilpejihyj/lovely-runner-s01e14-720p-amzn-web-dl-ddp2-0-h-264-daniewatch\" frameborder=\"0\" marginwidth=\"0\" marginheight=\"0\" scrolling=\"no\" width=\"640\" height=\"360\" allowfullscreen></iframe>"
        },
        {
          "episode_number": 15,
          "watch": "<iframe src=\"https://bysebuho.com/e/u27yvjkgy35c/lovely-runner-s01e15-720p-amzn-web-dl-ddp2-0-h-264-daniewatch\" frameborder=\"0\" marginwidth=\"0\" marginheight=\"0\" scrolling=\"no\" width=\"640\" height=\"360\" allowfullscreen></iframe>"
        },
        {
          "episode_number": 16,
          "watch": "<iframe src=\"https://bysebuho.com/e/tiro5logo69p/lovely-runner-s01e16-720p-amzn-web-dl-ddp2-0-h-264-daniewatch\" frameborder=\"0\" marginwidth=\"0\" marginheight=\"0\" scrolling=\"no\" width=\"640\" height=\"360\" allowfullscreen></iframe>"
        }
      ]
    }
  ]
}