{
    "post_title": "5lbs of Pressure",
    "post_type": "movie",
    "tmdb_id": 1079346,
    "imdb_id": "tt1524515",
    "languages": [
        "English"
    ],
    "links": {
        "480p": [
            {
                "episode_title": "Episode 1",
                "link": "https://hubdrive.tips/file/1710143753"
            }
        ],
        "720p": [
            {
                "episode_title": "Episode 1",
                "link": "https://hubdrive.tips/file/1710143756"
            }
        ]
    }
}