{
    "post_title": "Aakhri Sach",
    "post_type": "series",
    "tmdb_id": 232442,
    "imdb_id": "tt28638031",
    "languages": [
        "Hindi"
    ],
    "total_seasons": 1,
    "seasons": {
        "1": {
            "480p": [
                {
                    "episode_title": "Episode 1",
                    "link": "https://hubdrive.tips/file/1692905995"
                },
                {
                    "episode_title": "Episode 2",
                    "link": "https://hubdrive.tips/file/1692905994"
                },
                {
                    "episode_title": "Episode 3",
                    "link": "https://hubdrive.tips/file/1693519460"
                },
                {
                    "episode_title": "Episode 4",
                    "link": "https://hubdrive.tips/file/1694182205"
                },
                {
                    "episode_title": "Episode 5",
                    "link": "https://hubcloud.cx/drive/yihubywherrwbg_"
                },
                {
                    "episode_title": "Episode 6",
                    "link": "https://hubdrive.tips/file/1695336222"
                }
            ],
            "720p": [
                {
                    "episode_title": "Episode 1",
                    "link": "https://hubdrive.tips/file/1692905955"
                },
                {
                    "episode_title": "Episode 2",
                    "link": "https://hubdrive.tips/file/1692905954"
                },
                {
                    "episode_title": "Episode 3",
                    "link": "https://hubdrive.tips/file/1693519459"
                },
                {
                    "episode_title": "Episode 4",
                    "link": "https://hubdrive.tips/file/2153996363"
                },
                {
                    "episode_title": "Episode 5",
                    "link": "https://hubcloud.cx/drive/i0ozq1r0vl5z0e8"
                },
                {
                    "episode_title": "Episode 6",
                    "link": "https://hubdrive.tips/file/2023085028"
                }
            ],
            "1080p": [
                {
                    "episode_title": "Episode 1",
                    "link": "https://hubdrive.tips/file/1692905975"
                },
                {
                    "episode_title": "Episode 2",
                    "link": "https://hubdrive.tips/file/2666119919"
                },
                {
                    "episode_title": "Episode 3",
                    "link": "https://hubdrive.tips/file/2004053869"
                },
                {
                    "episode_title": "Episode 4",
                    "link": "https://hubdrive.tips/file/1694182204"
                },
                {
                    "episode_title": "Episode 5",
                    "link": "https://hubcloud.cx/drive/c5hnq5d40znnnjk"
                },
                {
                    "episode_title": "Episode 6",
                    "link": "https://hubdrive.tips/file/1695336221"
                }
            ]
        }
    }
}