{
    "post_title": "Camp Rock",
    "post_type": "movie",
    "tmdb_id": 13655,
    "imdb_id": "tt1055366",
    "languages": [
        "Hindi",
        "English"
    ],
    "links": {
        "480p": [
            {
                "episode_title": "Episode 1",
                "link": "https://hubdrive.tips/file/2084292081"
            }
        ],
        "720p": [
            {
                "episode_title": "Episode 1",
                "link": "https://hubdrive.tips/file/2209050006"
            }
        ],
        "1080p": [
            {
                "episode_title": "Episode 1",
                "link": "https://hubdrive.tips/file/3211276842"
            }
        ]
    }
}