{
    "post_title": "Encanto",
    "post_type": "movie",
    "tmdb_id": 568124,
    "imdb_id": "tt2953050",
    "languages": [
        "Hindi",
        "English"
    ],
    "links": {
        "480p": [
            {
                "episode_title": "Episode 1",
                "link": "https://hubdrive.tips/file/2154850677"
            }
        ],
        "720p": [
            {
                "episode_title": "Episode 1",
                "link": "https://hubdrive.tips/file/2314510864"
            }
        ],
        "1080p": [
            {
                "episode_title": "Episode 1",
                "link": "https://hubdrive.tips/file/2075365098"
            }
        ]
    }
}