{
    "post_title": "S.I.S. Special Investigation Section",
    "post_type": "movie",
    "tmdb_id": 75007,
    "imdb_id": "tt1077394",
    "languages": [
        "Hindi",
        "English"
    ],
    "links": {
        "480p": [
            {
                "episode_title": "Episode 1",
                "link": "https://hubdrive.tips/file/2017692402"
            }
        ],
        "720p": [
            {
                "episode_title": "Episode 1",
                "link": "https://hubdrive.tips/file/1983175395"
            }
        ]
    }
}