{
    "post_title": "Space Guardians 2",
    "post_type": "movie",
    "tmdb_id": 561589,
    "imdb_id": "tt8560130",
    "languages": [
        "Hindi",
        "English"
    ],
    "links": {
        "480p": [
            {
                "episode_title": "Episode 1",
                "link": "https://hubdrive.tips/file/2041615967"
            }
        ],
        "720p": [
            {
                "episode_title": "Episode 1",
                "link": "https://hubdrive.tips/file/2240407872"
            }
        ],
        "1080p": [
            {
                "episode_title": "Episode 1",
                "link": "https://hubdrive.tips/file/2928527296"
            }
        ]
    }
}