{
    "post_title": "Black Rock Shooter: Dawn Fall (2022)",
    "post_type": "series",
    "tmdb_id": 133733,
    "imdb_id": "tt15582422",
    "languages": [
        "Hindi",
        "Japanese"
    ],
    "total_seasons": 1,
    "seasons": {
        "1": {
            "720p": [
                {
                    "episode_title": "Episode 1",
                    "link": "https://vcloud.zip/yzsy41efdyfiei8"
                },
                {
                    "episode_title": "Episode 2",
                    "link": "https://vcloud.zip/kv3k700z-vub70a"
                },
                {
                    "episode_title": "Episode 3",
                    "link": "https://vcloud.zip/guevksqkss0tg-q"
                },
                {
                    "episode_title": "Episode 4",
                    "link": "https://vcloud.zip/8oooks1kbnxovxo"
                },
                {
                    "episode_title": "Episode 5",
                    "link": "https://vcloud.zip/4devooxcexf04on"
                },
                {
                    "episode_title": "Episode 6",
                    "link": "https://vcloud.zip/aln1iv8_mv1rxp1"
                },
                {
                    "episode_title": "Episode 7",
                    "link": "https://vcloud.zip/nqp6nmn2fblxnnj"
                },
                {
                    "episode_title": "Episode 8",
                    "link": "https://vcloud.zip/dgzqvyn0mmynt0a"
                },
                {
                    "episode_title": "Episode 9",
                    "link": "https://vcloud.zip/x181fexx1nnm11x"
                },
                {
                    "episode_title": "Episode 10",
                    "link": "https://vcloud.zip/wau1pl9jz4-arru"
                },
                {
                    "episode_title": "Episode 11",
                    "link": "https://vcloud.zip/rfol_49jet000k_"
                },
                {
                    "episode_title": "Episode 12",
                    "link": "https://vcloud.zip/dqi1j_xji_t0uqv"
                }
            ],
            "1080p": [
                {
                    "episode_title": "Episode 1",
                    "link": "https://vcloud.zip/fafrqt-klfaqppp"
                },
                {
                    "episode_title": "Episode 2",
                    "link": "https://vcloud.zip/pntpwyur2d_1edt"
                },
                {
                    "episode_title": "Episode 3",
                    "link": "https://vcloud.zip/hgneksx3nbxci1z"
                },
                {
                    "episode_title": "Episode 4",
                    "link": "https://vcloud.zip/ivaoiulg1lzucul"
                },
                {
                    "episode_title": "Episode 5",
                    "link": "https://vcloud.zip/ghpnnx9rpzgxaln"
                },
                {
                    "episode_title": "Episode 6",
                    "link": "https://vcloud.zip/dac9h15d0adyrea"
                },
                {
                    "episode_title": "Episode 7",
                    "link": "https://vcloud.zip/1m6ct46d1mj3me3"
                },
                {
                    "episode_title": "Episode 8",
                    "link": "https://vcloud.zip/vss_o8v9ososa0s"
                },
                {
                    "episode_title": "Episode 9",
                    "link": "https://vcloud.zip/piljm1cztwmstpe"
                },
                {
                    "episode_title": "Episode 10",
                    "link": "https://vcloud.zip/grhfyammh0synx_"
                },
                {
                    "episode_title": "Episode 11",
                    "link": "https://vcloud.zip/znnw1zlidgp21zd"
                },
                {
                    "episode_title": "Episode 12",
                    "link": "https://vcloud.zip/gamy1u6k1r9qtyw"
                }
            ]
        }
    }
}