{
    "post_title": "Case Closed: The Fourteenth Target (1998)",
    "post_type": "movie",
    "tmdb_id": 21452,
    "imdb_id": "tt0965649",
    "languages": [
        "Hindi",
        "English"
    ],
    "links": {
        "480p": [
            {
                "episode_title": "Episode 1",
                "link": "https://vcloud.zip/7zmvttsxvzv9nzz"
            }
        ],
        "720p": [
            {
                "episode_title": "Episode 1",
                "link": "https://vcloud.zip/hbhmhm2ihnidhg2"
            }
        ],
        "1080p": [
            {
                "episode_title": "Episode 1",
                "link": "https://vcloud.zip/oheteevppp4fqgi"
            }
        ]
    }
}