{
    "post_title": "Domain (2017)",
    "post_type": "movie",
    "tmdb_id": 406104,
    "imdb_id": "tt4694518",
    "languages": [
        "Hindi",
        "English"
    ],
    "links": {
        "480p": [
            {
                "episode_title": "Episode 1",
                "link": "https://vcloud.zip/o3w4-jbsnwfn1xs"
            }
        ],
        "720p": [
            {
                "episode_title": "Episode 1",
                "link": "https://vcloud.zip/ynwagkl4t-1htxc"
            }
        ],
        "1080p": [
            {
                "episode_title": "Episode 1",
                "link": "https://vcloud.zip/ppwzezewzyzywea"
            }
        ]
    }
}