{
    "post_title": "Dragon Wars: D-War (2007)",
    "post_type": "movie",
    "tmdb_id": 10253,
    "imdb_id": "tt0372873",
    "languages": [
        "Hindi"
    ],
    "links": {
        "480p": [
            {
                "episode_title": "Episode 1",
                "link": "https://vcloud.zip/wtwpne--9-ioiii"
            }
        ],
        "720p": [
            {
                "episode_title": "Episode 1",
                "link": "https://vcloud.zip/sgwonstscenj0sw"
            }
        ],
        "1080p": []
    }
}