{
    "post_title": "Feast II: Sloppy Seconds (2008)",
    "post_type": "movie",
    "tmdb_id": 13797,
    "imdb_id": "tt1104835",
    "languages": [
        "English"
    ],
    "links": {
        "480p": [
            {
                "episode_title": "Drive-[No Login]",
                "link": "https://vcloud.zip/api/index.php?link=czhBa0lmUVFrVmhJdHBVR3JXWmtRMFJRN09panAzTkVnbHF2NG5TbVBWcUFhQXB2VVZtVXVKUDV5TnRsR3JTNw=="
            }
        ],
        "720p": [
            {
                "episode_title": "Drive-[No Login]",
                "link": "https://vcloud.zip/api/index.php?link=eVM4eVBmaldVODQ5OFN2WUJwNzI1R2xvL1N3OVBMdzRjblBPMFVwUkxpSEkwT1diVFJ6b0RHQlJyMzl4UWpQMw=="
            }
        ],
        "1080p": []
    }
}