{
    "post_title": "Legend (2015)",
    "post_type": "movie",
    "tmdb_id": 276907,
    "imdb_id": "tt3569230",
    "languages": [
        "Hindi",
        "English"
    ],
    "links": {
        "480p": [
            {
                "episode_title": "Episode 1",
                "link": "https://vcloud.zip/1xrxrrx1xwx1unt"
            }
        ],
        "720p": [
            {
                "episode_title": "Episode 1",
                "link": "https://vcloud.zip/579zlqqw65c69c6"
            },
            {
                "episode_title": "Episode 2",
                "link": "https://vcloud.zip/iircfymvilexeyv"
            }
        ],
        "1080p": [
            {
                "episode_title": "Episode 1",
                "link": "https://vcloud.zip/fvcxoff4b_lgzxx"
            }
        ]
    }
}