{
    "post_title": "She Walks in Darkness (2025)",
    "post_type": "movie",
    "tmdb_id": 1275151,
    "imdb_id": "tt32129665",
    "languages": [
        "Hindi",
        "English"
    ],
    "links": {
        "480p": [
            {
                "episode_title": "Episode 1",
                "link": "https://vcloud.zip/mx4wffssaaejm4t"
            }
        ],
        "720p": [
            {
                "episode_title": "Episode 1",
                "link": "https://vcloud.zip/afxomdwrsmsxasm"
            }
        ],
        "1080p": [
            {
                "episode_title": "Episode 1",
                "link": "https://vcloud.zip/kvh21j2s8sdoj_k"
            }
        ]
    }
}