{
    "post_title": "The Mistress (2023)",
    "post_type": "movie",
    "tmdb_id": 1094713,
    "imdb_id": "tt13780990",
    "languages": [
        "Hindi",
        "English"
    ],
    "links": {
        "480p": [
            {
                "episode_title": "Episode 1",
                "link": "https://vcloud.zip/h88aaq1ms78hz8h"
            }
        ],
        "720p": [
            {
                "episode_title": "Episode 1",
                "link": "https://vcloud.zip/nk4zebdy6gfwfze"
            }
        ],
        "1080p": [
            {
                "episode_title": "Episode 1",
                "link": "https://vcloud.zip/bfx6xgbpx5uk5vi"
            }
        ]
    }
}