{
    "post_title": "The Little Rascals (1994)",
    "post_type": "movie",
    "tmdb_id": 10897,
    "imdb_id": "tt0110366",
    "languages": [
        "Hindi",
        "English"
    ],
    "links": {
        "480p": [
            {
                "episode_title": "Episode 1",
                "link": "https://vcloud.zip/dw9zwwdxuwe8fqr"
            }
        ],
        "720p": [
            {
                "episode_title": "Episode 1",
                "link": "https://vcloud.zip/irrg_bfyj61b65j"
            }
        ],
        "1080p": []
    }
}