{
    "post_title": "Welcome to Earth (2021)",
    "post_type": "series",
    "tmdb_id": 127700,
    "imdb_id": "tt13623992",
    "languages": [
        "English"
    ],
    "total_seasons": 1,
    "seasons": {
        "1": {
            "720p": [
                {
                    "episode_title": "Episode 1",
                    "link": "https://vcloud.zip/zxzesim-8ghlvhx"
                },
                {
                    "episode_title": "Episode 2",
                    "link": "https://vcloud.zip/1pzfitivosri1v_"
                },
                {
                    "episode_title": "Episode 3",
                    "link": "https://vcloud.zip/migrmio6m-cixov"
                },
                {
                    "episode_title": "Episode 4",
                    "link": "https://vcloud.zip/pn1zq7tff3cnc66"
                },
                {
                    "episode_title": "Episode 5",
                    "link": "https://vcloud.zip/7-u11_b44v__p0k"
                },
                {
                    "episode_title": "Episode 6",
                    "link": "https://vcloud.zip/twwpcmbh32ykwnf"
                }
            ]
        }
    }
}